srfnef/__init__.py
srfnef/adapter.py
srfnef/func_types.py
srfnef/typing.py
srfnef/utils.py
srfnef/version.py
srfnef/app/__init__.py
srfnef/app/cli.py
srfnef/correction/__init__.py
srfnef/correction/attenuation.py
srfnef/correction/psf.py
srfnef/correction/sensitivity.py
srfnef/correction/psf/__init__.py
srfnef/correction/psf/deconvolutor.py
srfnef/correction/psf/psf.py
srfnef/correction/psf/psf_fitter.py
srfnef/correction/scatter/__init__.py
srfnef/correction/scatter/listmode2sinogram.py
srfnef/correction/scatter/preprocess.py
srfnef/correction/scatter/scatter.py
srfnef/correction/scatter/scatter_fraction/__init__.py
srfnef/correction/scatter/scatter_fraction/kn_formula.py
srfnef/correction/scatter/scatter_fraction/scatter_fraction.py
srfnef/data_types/__init__.py
srfnef/data_types/_mesh_grid.py
srfnef/data_types/emap.py
srfnef/data_types/image.py
srfnef/data_types/projection.py
srfnef/data_types/scanner.py
srfnef/data_types/umap.py
srfnef/db/__init__.py
srfnef/db/_api.py
srfnef/db/api.py
srfnef/db/db_operators.py
srfnef/db/postgresql/__init__.py
srfnef/db/postgresql/add_object.py
srfnef/db/postgresql/config.py
srfnef/db/postgresql/create_schema.py
srfnef/db/postgresql/select_object.py
srfnef/model_impl/__init__.py
srfnef/model_impl/_bproj_siddon.py
srfnef/model_impl/_proj_siddon.py
srfnef/tools/__init__.py
srfnef/tools/imshow_full.py
srfnef-0.6.2.1.1554711060.dist-info/LICENCE
srfnef-0.6.2.1.1554711060.dist-info/METADATA
srfnef-0.6.2.1.1554711060.dist-info/WHEEL
srfnef-0.6.2.1.1554711060.dist-info/entry_points.txt
srfnef-0.6.2.1.1554711060.dist-info/top_level.txt
srfnef-0.6.2.1.1554711060.dist-info/RECORD
