Metadata-Version: 2.1
Name: srfnef
Version: 0.6.2.1.1554711060
Summary: Scalable Reconstruction Framework -- Not Enough Functions
Home-page: UNKNOWN
Author: Minghao Guo
Author-email: mh.guo0111@gmail.com
License: Apache
Platform: UNKNOWN
Requires-Dist: scipy
Requires-Dist: matplotlib
Requires-Dist: typing
Requires-Dist: h5py
Requires-Dist: click
Requires-Dist: numpy
Requires-Dist: tqdm
Requires-Dist: numba
Requires-Dist: deepdish (==0.3.6)
Requires-Dist: Click
